requirements_score/__init__.py
requirements_score/exceptions.py
requirements_score/management.py
requirements_score/tests/__init__.py
requirements_score/tests/test_requirements_score.py
requirements_score-0.0.1.dist-info/LICENSE
requirements_score-0.0.1.dist-info/METADATA
requirements_score-0.0.1.dist-info/WHEEL
requirements_score-0.0.1.dist-info/entry_points.txt
requirements_score-0.0.1.dist-info/top_level.txt
requirements_score-0.0.1.dist-info/RECORD
