Metadata-Version: 2.1
Name: requirements-score
Version: 0.0.1
Summary: Check the health of your project's requirements and get a score for each dependency.
Home-page: https://github.com/Nekmo/requirements-score/
Download-URL: https://github.com/Nekmo/requirements-score/archive/master.zip
Author: Nekmo
Author-email: contacto@nekmo.com
License: MIT license
Keywords: requirements-score
Platform: any
Classifier: Development Status :: 3 - Alpha
Classifier: Programming Language :: Python :: 3 :: Only
Classifier: Programming Language :: Python :: 3.7
Classifier: Programming Language :: Python :: 3.8
Classifier: Programming Language :: Python :: 3.9
Classifier: Programming Language :: Python :: 3.10
Classifier: Operating System :: POSIX :: Linux
Classifier: Operating System :: MacOS :: MacOS X
Classifier: Operating System :: Microsoft :: Windows
Classifier: Operating System :: POSIX :: SunOS/Solaris
Classifier: Operating System :: POSIX :: BSD
Classifier: License :: OSI Approved :: MIT License
Classifier: Natural Language :: English
License-File: LICENSE
Requires-Dist: click (>=6.0)
